MANIFEST.in
README.md
setup.cfg
setup.py
dj_vault.egg-info/PKG-INFO
dj_vault.egg-info/SOURCES.txt
dj_vault.egg-info/dependency_links.txt
dj_vault.egg-info/requires.txt
dj_vault.egg-info/top_level.txt
django_vault/__init__.py
django_vault/admin.py
django_vault/client.py
django_vault/forms.py